vpack/__init__.py
vpack/breakpt.py
vpack/reload.py
vpack/sigview.py
vpack/utils.py
vpack-0.0.11.dist-info/LICENSE
vpack-0.0.11.dist-info/METADATA
vpack-0.0.11.dist-info/WHEEL
vpack-0.0.11.dist-info/top_level.txt
vpack-0.0.11.dist-info/RECORD
