Metadata-Version: 2.1
Name: vpack
Version: 0.0.11
Summary: A package containing many useful utilities
Home-page: https://github.com/volltin/vpack
Author: Volltin
Author-email: volltin@live.com
License: UNKNOWN
Project-URL: Bug Tracker, https://github.com/volltin/vpack/issues
Platform: UNKNOWN
Classifier: Programming Language :: Python :: 3
Classifier: License :: OSI Approved :: MIT License
Classifier: Operating System :: OS Independent
Requires-Python: >=3.6
License-File: LICENSE
Requires-Dist: colorama
Requires-Dist: pygments
